weni_utils/__init__.py
weni_utils/tools/__init__.py
weni_utils/tools/client.py
weni_utils/tools/concierge.py
weni_utils/tools/context.py
weni_utils/tools/functions.py
weni_utils/tools/orders.py
weni_utils/tools/py.typed
weni_utils/tools/stock.py
weni_utils/tools/plugins/__init__.py
weni_utils/tools/plugins/base.py
weni_utils/tools/plugins/capi.py
weni_utils/tools/plugins/carousel.py
weni_utils/tools/plugins/cart_simulation.py
weni_utils/tools/plugins/regionalization.py
weni_utils/tools/plugins/send_message.py
weni_utils/tools/plugins/utils.py
weni_utils/tools/plugins/weni_flow.py
weni_utils/tools/plugins/wholesale.py
weni_utils_tools-0.0.1.dist-info/licenses/LICENSE
weni_utils_tools-0.0.1.dist-info/METADATA
weni_utils_tools-0.0.1.dist-info/WHEEL
weni_utils_tools-0.0.1.dist-info/top_level.txt
weni_utils_tools-0.0.1.dist-info/RECORD
