Metadata-Version: 2.4
Name: weni-utils-tools
Version: 0.0.1
Summary: Modular tools library for AI agents on the Weni platform
Author-email: Weni AI <dev@weni.ai>
Maintainer-email: Weni AI <dev@weni.ai>
License: MIT
Project-URL: Homepage, https://github.com/weni-ai/tools-utils
Project-URL: Documentation, https://github.com/weni-ai/tools-utils#readme
Project-URL: Repository, https://github.com/weni-ai/tools-utils.git
Project-URL: Issues, https://github.com/weni-ai/tools-utils/issues
Project-URL: Changelog, https://github.com/weni-ai/tools-utils/blob/main/CHANGELOG.md
Keywords: weni,vtex,ecommerce,ai-agent,chatbot,whatsapp,product-search,intelligent-search,tools
Classifier: Development Status :: 3 - Alpha
Classifier: Intended Audience :: Developers
Classifier: License :: OSI Approved :: MIT License
Classifier: Operating System :: OS Independent
Classifier: Programming Language :: Python :: 3
Classifier: Programming Language :: Python :: 3.9
Classifier: Programming Language :: Python :: 3.10
Classifier: Programming Language :: Python :: 3.11
Classifier: Programming Language :: Python :: 3.12
Classifier: Programming Language :: Python :: 3.13
Classifier: Topic :: Software Development :: Libraries :: Python Modules
Classifier: Topic :: Internet :: WWW/HTTP
Classifier: Topic :: Communications :: Chat
Classifier: Typing :: Typed
Requires-Python: >=3.9
License-File: LICENSE
Requires-Dist: requests<3.0.0,>=2.28.0
Requires-Dist: pytz>=2023.3
Provides-Extra: dev
Requires-Dist: pytest>=7.0.0; extra == "dev"
Requires-Dist: pytest-cov>=4.0.0; extra == "dev"
Requires-Dist: pytest-mock>=3.10.0; extra == "dev"
Requires-Dist: responses>=0.23.0; extra == "dev"
Requires-Dist: black==24.10.0; extra == "dev"
Requires-Dist: isort==5.13.2; extra == "dev"
Requires-Dist: mypy>=1.0.0; extra == "dev"
Requires-Dist: types-requests>=2.28.0; extra == "dev"
Requires-Dist: ruff>=0.1.0; extra == "dev"
Provides-Extra: docs
Requires-Dist: sphinx>=6.0.0; extra == "docs"
Requires-Dist: sphinx-rtd-theme>=1.2.0; extra == "docs"
Requires-Dist: myst-parser>=1.0.0; extra == "docs"
Dynamic: license-file
